inventree_report_lsp_plugin-0.1.2.dist-info/licenses/LICENSE
report_lsp/__init__.py
report_lsp/core.py
report_lsp/custom_collector.py
report_lsp/lsp/__init__.py
report_lsp/lsp/server.py
report_lsp/static/report-lsp.dev.js
report_lsp/static/dist/main.js
report_lsp/static/dist/assets/_.contribution-BThlLkzn.js
report_lsp/static/dist/assets/_commonjsHelpers-CqkleIqs.js
report_lsp/static/dist/assets/dark_modern.json
report_lsp/static/dist/assets/dark_vs.json
report_lsp/static/dist/assets/editor-BUXrGX5P.js
report_lsp/static/dist/assets/editor.worker-CMjhB8I4.js
report_lsp/static/dist/assets/emmetBrowserMain.js
report_lsp/static/dist/assets/emmetBrowserMain.js.map
report_lsp/static/dist/assets/extensionHost.worker-DGUebB9u.js
report_lsp/static/dist/assets/fake.html
report_lsp/static/dist/assets/files.contribution._fileEditorFactory-Bj2Ckw7Y.js
report_lsp/static/dist/assets/hc_black.json
report_lsp/static/dist/assets/hc_light.json
report_lsp/static/dist/assets/html.tmLanguage.json
report_lsp/static/dist/assets/htmlClientMain.js
report_lsp/static/dist/assets/htmlClientMain.js.map
report_lsp/static/dist/assets/htmlServerMain.js
report_lsp/static/dist/assets/htmlServerMain.js.map
report_lsp/static/dist/assets/icon.png
report_lsp/static/dist/assets/iconv-lite-umd-9oYrSzTT.js
report_lsp/static/dist/assets/index-Biporm2x.js
report_lsp/static/dist/assets/index-BrnO8Xg5.js
report_lsp/static/dist/assets/index-C2PBHf53.js
report_lsp/static/dist/assets/index-CFEpB1Lb.js
report_lsp/static/dist/assets/index-C_xS_3vi.js
report_lsp/static/dist/assets/index-DaNYZ1PO.js
report_lsp/static/dist/assets/index-DdYQAt_c.js
report_lsp/static/dist/assets/index-no-csp.html
report_lsp/static/dist/assets/index-tm7wD1Pq.js
report_lsp/static/dist/assets/index.html
report_lsp/static/dist/assets/jquery.d.ts.txt
report_lsp/static/dist/assets/layout.contribution.darwin-gdaUfoJf.js
report_lsp/static/dist/assets/layout.contribution.linux-xMjRz7iy.js
report_lsp/static/dist/assets/layout.contribution.win-DZRWibbm.js
report_lsp/static/dist/assets/light_modern.json
inventree_report_lsp_plugin-0.1.2.dist-info/METADATA
inventree_report_lsp_plugin-0.1.2.dist-info/WHEEL
inventree_report_lsp_plugin-0.1.2.dist-info/entry_points.txt
inventree_report_lsp_plugin-0.1.2.dist-info/top_level.txt
inventree_report_lsp_plugin-0.1.2.dist-info/RECORD
