Metadata-Version: 2.4
Name: inventree-report-lsp-plugin
Version: 0.1.2
Summary: A report editor plugin that is powered by an LSP
Author-email: wolflu05 <76838159+wolflu05@users.noreply.github.com>
License-Expression: GPL-3.0+
Project-URL: Homepage, https://github.com/wolflu05/inventree-report-lsp-plugin
Keywords: inventree,plugin
Classifier: Programming Language :: Python :: 3
Classifier: Operating System :: OS Independent
Classifier: Framework :: InvenTree
Requires-Python: >=3.9
License-File: LICENSE
Requires-Dist: websockets==15.0.1
Requires-Dist: pyjwt==2.10.1
Requires-Dist: django-template-lsp==1.2.2
Dynamic: license-file
